Workbook

Sheet README
A1: ROCK Pi S Hybrid Smart Water Controller - Shopping, Build and Config Workbook
A2: Hybrid of Scenario A (hardwired safety) and Scenario B (wireless ESP-NOW garden). Prepared 11 Oct 2026.
A4: Sheet | B4: What it contains
A5: BOM | B5: Every component with quantity, cost range, why it is needed, specification, where to install, how to do it, config, Amazon.in link, cheaper options and cart status. Filter by section or status.
A6: Totals | B6: Cost totals by section (formulas), item counts, and counts by cart status.
A7: Wiring & Pinout | B7: Head-end and garden I/O maps, the hardware interlock chain and the power tree.
A8: Setup Steps | B8: Ordered build procedure: what to do, where, how, and the values to configure.
A9: Config Reference | B9: Software and hardware settings with suggested defaults.
A10: Commissioning Tests | B10: Tests to run, in order, before trusting the system with the real motor.
A11: Cart Cross-check | B11: Problems found in your Amazon cart, with the fix for each.
A13: Legend
A14: Blue text | B14: Hardcoded input you can edit (cost estimates, quantity to deduct).
A15: Black text | B15: Formula or descriptive text.
A16: Orange fill | B16: Needs attention: wrong item, risky item or unverified value.
A18: Assumptions
A19: Costs | B19: My estimated Indian market ranges in INR for the quantity shown (total, not per unit). They are not live prices. Check current listings.
A20: Amazon links | B20: Amazon.in SEARCH links, not specific product pages. Compare listings and sellers before buying.
A21: GPIO / pins | B21: ROCK Pi S GPIO numbers come from the earlier master prompt and are UNVERIFIED. Run gpioinfo and the official Radxa pinout before wiring. ESP32-C3 pins are suggestions.
A22: Config values | B22: All thresholds, timeouts and limits are suggested defaults. Calibrate each soil probe and tune after testing.
A23: Safety | B23: I am not a licensed electrician. Have the 220V side (MCB, RCCB, SPD, contactor, overload, earthing, motor wiring) installed and checked by a qualified electrician.
A24: Rows added since the earlier list | B24: DIN-rail terminal blocks, PG11/PG13.5 glands and pump outlet reducers were added. WAGO cost now assumes genuine WAGO.

Sheet BOM
A1: Bill of Materials with install detail
A2: Cost = estimated total for the quantity shown (INR). Edit blue cost cells to match real prices; Totals recalculates.
A4: # | B4: Section | C4: Component | D4: Qty | E4: Cost low (INR, est.) | F4: Cost high (INR, est.) | G4: Why it's needed | H4: Specification | I4: Where to install / use | J4: How to do it (steps) | K4: Config / settings | L4: Amazon.in | M4: Check for cheaper | N4: Cart status
A5: 1 | B5: 1. Controller head-end | C5: SanDisk Max Endurance 32GB microSD | D5: 1 | E5: 650 | F5: 750 | G5: OS storage built for constant writes, which lowers the risk of SD card corruption. | H5: 32GB, Class 10, A1, high-endurance (dash-cam / monitoring grade). | I5: ROCK Pi S microSD slot. | J5: 1) Flash Armbian or Debian minimal CLI with balenaEtcher. 2) First boot, expand filesystem, update. 3) Keep logs small to reduce wear. | K5: Hostname waterctl. DHCP reservation or static IP. journald SystemMaxUse=50M. SQLite in WAL mode (PRAGMA journal_mode=WAL). | L5: Amazon.in search | M5: Flipkart, local SanDisk dealer | N5: Missing from cart
A6: 2 | B6: 1. Controller head-end | C6: CM108 USB audio dongle | D6: 1 | E6: 180 | F6: 250 | G6: The ROCK Pi S has no audio jack, so this gives the speaker a clean analog output. | H6: USB 2.0 class-compliant, C-Media CM108, 3.5mm line-out. | I6: Powered USB hub port. | J6: 1) Plug into the hub. 2) Run aplay -l to find the card number. 3) Test with speaker-test -t wav -c 1. | K6: Set the default ALSA card in /etc/asound.conf (pcm.!default and ctl.!default pointing at the CM108 card). Adjust volume with alsamixer. | L6: Amazon.in search | M6: Robu.in, Robocraze | N6: Missing from cart
A7: 3 | B7: 1. Controller head-end | C7: 3-5W USB speaker | D7: 1 | E7: 300 | F7: 450 | G7: Plays spoken voice alerts (tank full, dry-run, broken probe). | H7: 3-5W, USB-powered (5V, under 500mA), 3.5mm audio input. | I7: Near the living area or head-end, cabled to the CM108 dongle. | J7: 1) Power from a hub USB port. 2) Connect 3.5mm to the dongle. 3) Test: espeak-ng -s 145 'Tank full' --stdout | aplay -q | K7: Volume about 70 percent. Daemon announces with espeak-ng -s 145 then aplay -q. | L7: Amazon.in search | M7: Flipkart | N7: Missing from cart
A8: 4 | B8: 1. Controller head-end | C8: Powered USB 2.0 hub | D8: 1 | E8: 350 | F8: 550 | G8: Powers the speaker, audio dongle and ESP32 gateway without drawing from the board's USB port, which could brown it out. | H8: 4-port, with its OWN 5V 2A DC input jack. A slim bus-powered hub does not meet this. | I8: Head-end logic enclosure. | J8: 1) Power the hub from the 5V rail (buck) or its adapter via the UPS-fed 5V. 2) Plug the hub into the ROCK Pi S USB host. 3) Connect dongle, speaker, ESP32 gateway to the hub. | K8: None. Confirm the cart item has a DC input before relying on it. | L8: Amazon.in search | M8: Flipkart | N8: In cart - verify
A9: 5 | B9: 1. Controller head-end | C9: 12V mini-UPS | D9: 1 | E9: 1200 | F9: 1650 | G9: Keeps the controller running through load shedding, so it does not reboot with relays in an unknown state. | H9: 12V output, 2A (router-class), 18650 cells, about 3 hr backup at router load. | I9: Head-end enclosure or beside it. | J9: 1) Plug the UPS into mains. 2) Feed its 12V output through a 2A fuse to the buck converter input. 3) Power only the logic (Pi, hub, relay), never the pumps. | K9: Keep total 12V draw under 2A (the Pi side draws about 0.5A at 12V). Test by pulling mains: the Pi must stay up. | L9: Amazon.in search | M9: Flipkart, brand store | N9: In cart
A10: 6 | B10: 1. Controller head-end | C10: LM2596 / MP1584EN buck converter (head-end) | D10: 1 | E10: 80 | F10: 120 | G10: Steps the UPS's 12V down to a regulated 5.1V for the ROCK Pi S. | H10: LM2596: in 4-35V, out 1.25-35V, 3A. MP1584EN: in 4.5-28V, 3A max. Set output 5.1V. | I10: Head-end logic enclosure. | J10: 1) Connect input only. 2) With a multimeter on the output, turn the trimmer to 5.10V BEFORE connecting the load. 3) Seal the trimmer with nail polish. 4) Feed the Pi via a USB-C power pigtail. | K10: Vout = 5.10V. Fuse 2A on the output. Check polarity twice. | L10: Amazon.in search | M10: Robu.in, Robocraze | N10: In cart
A11: 7 | B11: 1. Controller head-end | C11: DS3231 RTC module | D11: 1 | E11: 150 | F11: 250 | G11: The board loses the time on power cut, which would break schedules and cooldown timers when there is no internet. | H11: I2C address 0x68, accuracy about 2ppm, 3.3V supply, CR2032 / LIR2032 backup. | I11: ROCK Pi S header I2C pins (3 SDA, 5 SCL, to verify). | J11: 1) Wire VCC 3.3V, GND, SDA, SCL. 2) Enable the I2C overlay. 3) i2cdetect -y <bus> shows 68. 4) Bind the driver and sync: hwclock --systohc after NTP. | K11: Use an LIR2032 or remove the charging resistor if using a CR2032 (it can swell). Use monotonic timers for lockouts as well. | L11: Amazon.in search | M11: Robu.in, Sunrom | N11: In cart - verify
A12: 8 | B12: 1. Controller head-end | C12: Inline fuse holders and fuses | D12: 2 | E12: 60 | F12: 100 | G12: Protects the 12V and 5V rails from short circuits and fire. | H12: 5x20mm glass fuse, inline holder. Assortment 1A, 2A, 3A, 5A fast-blow. | I12: UPS 12V output, head-end 5V output, garden 12V input. | J12: 1) Cut the positive lead and insert the holder. 2) Fit the fuse for that rail. 3) Label the holder. | K12: UPS 12V out: 2A. Head-end 5V: 2A. Garden 12V: 3A. The 10A fuse pack in the cart is too large for these rails. | L12: Amazon.in search | M12: Local electronics shop | N12: In cart - fix
A13: 9 | B13: 1. Controller head-end | C13: 4-channel optocoupler module | D13: 1 | E13: 120 | F13: 180 | G13: Isolates the long float and sensor cables from the Pi's GPIO, so a surge does not destroy the board. | H13: PC817, 4 channels. Check the input range on the listing (about 3-24V). Output side runs on the Pi's 3.3V. | I13: Head-end logic enclosure. | J13: 1) Wire each float loop (5V fused, through the float, to the opto input). 2) Opto output to a Pi GPIO input. 3) Add a TVS across each input pair. | K13: Outputs read active-low. Enable internal pull-ups in libgpiod and debounce 100ms in software. | L13: Amazon.in search | M13: Robu.in, Robocraze | N13: In cart
A14: 10 | B14: 1. Controller head-end | C14: TVS diodes P6KE18CA (bidirectional) | D14: 6 | E14: 30 | F14: 60 | G14: Clamp voltage spikes induced on the long sensor cables. | H14: P6KE18CA, 600W, bidirectional, about 18V breakdown. Cart has a 12-piece pack. | I14: Across each sensor wire pair at the controller end. | J14: 1) Solder one TVS between the signal wire and ground at the terminal block of each long cable. 2) Keep the leads short. | K14: No setting. Use one per long wire pair (tank low, interlock nodes, sump, leak). | L14: Amazon.in search | M14: Electronicscomp, local shop | N14: In cart
A15: 11 | B15: 1. Controller head-end | C15: Water leak sensor (digital, LM393) | D15: 1 | E15: 60 | F15: 120 | G15: Detects leaks or flooding in the enclosure area. | H15: 3.3-5V, with LM393 comparator and DO output pin. The cart's REL_35 is analog and not suitable. | I15: Floor of the head-end enclosure or under the garden box. | J15: 1) Place the probe flat at the lowest point. 2) Connect DO to opto channel 4. 3) Adjust the pot until a wet finger trips it. | K15: Alarm action: stop all pumps and speak an alert. Power at 3.3V. | L15: Amazon.in search | M15: Robu.in, Robocraze | N15: In cart - fix
A16: 12 | B16: 1. Controller head-end | C16: Logic enclosure IP65 200x150x100 | D16: 1 | E16: 450 | F16: 650 | G16: Weatherproof, dust-proof housing for the Pi and logic boards, kept separate from mains. | H16: IP65 ABS, 200x150x100 mm, clear or grey lid. | I16: Wall near the motor starter, but separate from the mains enclosure. | J16: 1) Plan the layout. 2) Drill gland holes in the bottom face only. 3) Mount standoffs for the Pi and perfboard. | K16: Keep at least 5 cm from mains wiring and never run mains inside this box. | L16: Amazon.in search | M16: IndiaMART, local electrical shop | N16: Missing from cart
... A64: 60 | B64: 5. Optional extras | C64: Extra ADS1115 (address 0x49) | D64: 1 | E64: 200 | F64: 280 | G64: Adds 4 more analog channels, which takes you from 4 to 8 plant zones. | H64: Same as above, with ADDR pin to VDD for address 0x49. | I64: Garden enclosure. | J64: 1) Tie ADDR to VDD. 2) Share the I2C bus. 3) Add 4 more soil sensors and pumps. | K64: Each plant needs one MOSFET channel as well. | L64: Amazon.in search | M64: Robu.in, Sunrom | N64: In cart

Sheet Totals
A1: Cost totals and item counts
A2: All figures are formulas over the BOM sheet.
A4: Section | B4: Line items | C4: Cost low (INR) | D4: Cost high (INR)
A5: 1. Controller head-end | B5: =COUNTIF(BOM!$B$5:$B$64,A5) -> 19 | C5: =SUMIFS(BOM!$E$5:$E$64,BOM!$B$5:$B$64,A5) -> 4685 | D5: =SUMIFS(BOM!$F$5:$F$64,BOM!$B$5:$B$64,A5) -> 6725
A6: 2. Mains & motor control | B6: =COUNTIF(BOM!$B$5:$B$64,A6) -> 14 | C6: =SUMIFS(BOM!$E$5:$E$64,BOM!$B$5:$B$64,A6) -> 4480 | D6: =SUMIFS(BOM!$F$5:$F$64,BOM!$B$5:$B$64,A6) -> 7470
A7: 3. Hardwired sensors | B7: =COUNTIF(BOM!$B$5:$B$64,A7) -> 4 | C7: =SUMIFS(BOM!$E$5:$E$64,BOM!$B$5:$B$64,A7) -> 2200 | D7: =SUMIFS(BOM!$F$5:$F$64,BOM!$B$5:$B$64,A7) -> 3920
A8: 4. Wireless garden station | B8: =COUNTIF(BOM!$B$5:$B$64,A8) -> 18 | C8: =SUMIFS(BOM!$E$5:$E$64,BOM!$B$5:$B$64,A8) -> 3380 | D8: =SUMIFS(BOM!$F$5:$F$64,BOM!$B$5:$B$64,A8) -> 4840
A9: Core hybrid total (sections 1-4) | B9: =SUM(B5:B8) -> 55 | C9: =SUM(C5:C8) -> 14745 | D9: =SUM(D5:D8) -> 22955
A10: 5. Optional extras | B10: =COUNTIF(BOM!$B$5:$B$64,A10) -> 5 | C10: =SUMIFS(BOM!$E$5:$E$64,BOM!$B$5:$B$64,A10) -> 1645 | D10: =SUMIFS(BOM!$F$5:$F$64,BOM!$B$5:$B$64,A10) -> 2590
A11: Core plus optional extras | B11: =B9+B10 -> 60 | C11: =C9+C10 -> 16390 | D11: =D9+D10 -> 25545
A13: Less: parts you already own (enter amounts) | C13: 0 | D13: 0
A14: Core total after deductions | C14: =C9-C13 -> 14745 | D14: =D9-D13 -> 22955
A15: Core + optional after deductions | C15: =C11-C13 -> 16390 | D15: =D11-D13 -> 25545
A16: Deductions: enter what you already own (for example the contactor, about 850-1,200). The ROCK Pi S is already excluded (owned).
A18: Cart status | B18: Line items
A19: In cart | B19: =COUNTIF(BOM!$N$5:$N$64,"In cart") -> 25
A20: In cart, needs a fix or check | B20: =COUNTIF(BOM!$N$5:$N$64,"In cart*")-COUNTIF(BOM!$N$5:$N$64,"In cart") -> 17
A21: Partly in cart | B21: =COUNTIF(BOM!$N$5:$N$64,"Partly*") -> 3
A22: Missing from cart | B22: =COUNTIF(BOM!$N$5:$N$64,"Missing*") -> 15
A23: Total line items | B23: =SUM(B19:B22) -> 60
A25: Check: total line items should equal Core + optional line items above. | B25: =IF(B23=B11,"OK","MISMATCH") -> OK

Sheet Wiring & Pinout
A1: Wiring and pinout
A2: ROCK Pi S GPIO numbers are carried from the earlier prompt and are UNVERIFIED. Run gpioinfo before wiring. ESP32-C3 pins are suggestions.
A4: A. ROCK Pi S head-end I/O
A5: Signal | B5: Direction | C5: Connected to | D5: Header pin / line (unverified) | E5: Notes
A6: Tank Low float | B6: Input | C6: Float loop > opto channel 1 > GPIO (pull-up, active-low) | D6: Pin 11 / line 10 (earlier prompt) | E6: Debounce 100ms. Low = start motor if all interlocks are healthy.
A7: Interlock chain output | B7: Input | C7: Relay VCC node after Full + Sump floats > opto channel 2 | D7: Pin 13 / line 11 (earlier prompt) | E7: High means the chain is closed and the motor is allowed. Low means Full or Sump tripped.
A8: Interlock mid-point | B8: Input | C8: Node between Full and Sump floats > opto channel 3 | D8: Pin 15 / line 12 (earlier prompt) | E8: Lets the software tell Full from Sump. Mid-point high and output low means the Sump tripped.
A9: Leak sensor | B9: Input | C9: Leak sensor DO > opto channel 4 | D9: Free input pin, to choose | E9: Alarm: stop all pumps and speak an alert.
A10: Contactor pilot relay | B10: Output | C10: Relay module IN (in the mains enclosure) | D10: Pin 16 / line 13 (earlier prompt) | E10: 10k pull-down to GND. Must be OFF at boot and at watchdog reset. Verify module polarity.
A11: I2C SDA / SCL | B11: Bus | C11: DS3231 RTC (0x68), OLED (0x3C, optional) | D11: Pins 3 and 5, I2C7 (earlier prompt) | E11: Enable the overlay; confirm the bus number with i2cdetect -l.
A12: USB host | B12: Bus | C12: Powered hub > CM108 audio, ESP32-C3 gateway (/dev/ttyACM0) | D12: USB-A port | E12: Speaker and dongle powered from the hub.
A13: Power in | B13: Power | C13: Buck 5.1V > USB-C power pigtail | D13: USB-C | E13: Fuse 2A. Set 5.10V before connecting.
A15: B. Garden node ESP32-C3 Super Mini (suggested pins)
A16: Signal | B16: Direction | C16: Connected to | D16: ESP32-C3 GPIO (suggested) | E16: Notes
A17: I2C SDA | B17: Bus | C17: ADS1115 SDA | D17: GPIO6 | E17: ADS1115 at 0x48, powered from the ESP32 3V3.
A18: I2C SCL | B18: Bus | C18: ADS1115 SCL | D18: GPIO7 | E18: Add 4.7k pull-ups if the module lacks them.
A19: Soil 1-4 | B19: Analog | C19: ADS1115 A0, A1, A2, A3 | D19: n/a | E19: Sensor VCC 3.3V. Output must stay under 3.3V.
A20: Pump 1-4 gates | B20: Output | C20: MOSFET IN1-IN4 with 10k pull-down each | D20: GPIO0, GPIO1, GPIO3, GPIO10 | E20: Avoid GPIO2, GPIO8, GPIO9 (strapping pins).
A21: Reservoir float | B21: Input | C21: Float between GPIO and GND | D21: GPIO5 (INPUT_PULLUP) | E21: Wet = LOW. Dry = HIGH = pumps locked out.
A22: Flow meter pulse | B22: Input | C22: YF-S401 signal through a 10k / 20k divider | D22: GPIO4 | E22: Divider brings 5V down to about 3.3V.
A23: Power | B23: Power | C23: 12V 3A adapter > fuse > MOSFET V+ and buck; buck 5.0V > ESP32 5V pin | D23: 5V pin | E23: Common ground between buck, MOSFET board and ESP32.
A25: C. Hardware interlock chain (overflow and dry-run cut-off)
A26: Step | B26: From | C26: To | D26: Detail | E26: Why
A27: 1 | B27: Fused 5V (buck) | C27: Full float (NC) | D27: Closed while water is below full. Opens at full or if the wire is cut. | E27: Hardware overflow cut-off that works even if the Pi has crashed.
A28: 2 | B28: Full float | C28: Sump float (NO) | D28: Closed when water is present in the sump. Opens when dry. | E28: Hardware dry-run cut-off for the main motor.
A29: 3 | B29: Sump float | C29: Relay module VCC (or JD-VCC if the module has the jumper) | D29: Break the relay coil supply, not the 220V side. | E29: Float contacts only carry milliamps at 5V.
A30: 4 | B30: Node after Full float | C30: Opto channel 3 | D30: Senses the mid-point. | E30: Tells the software which float tripped.
A31: 5 | B31: Node after Sump float | C31: Opto channel 2 | D31: Senses the chain output. | E31: Tells the software the motor is allowed.
A32: 6 | B32: Electrician review | C32: n/a | D32: Confirm the module's VCC powers the coil, and the selector's Manual path. | E32: Safety sign-off before first run.
A34: D. Power tree
A35: Branch | B35: Path | C35: Protection | D35: Load | E35: Notes
A36: Motor circuit | B36: Mains > MCB 16A > RCCB 30mA > contactor > overload relay > motor | C36: MCB, RCCB, SPD, overload | D36: Motor (about 0.5-1.5 HP) | E36: Electrician installs. No WAGO connectors.
A37: Logic | B37: Mains > UPS 12V > 2A fuse > buck 5.1V > ROCK Pi S, hub, relay | C37: 2A fuses | D37: About 0.5A at 12V | E37: UPS keeps this alive in load shedding.
A38: Garden pumps | B38: Mains socket > 12V 3A adapter > 3A fuse > MOSFET board > pumps | C38: 3A fuse, flyback diodes | D38: About 1A for 4 pumps | E38: Run at most two pumps at once.
A39: Garden logic | B39: 12V rail > buck 5.0V > ESP32 5V pin > 3V3 > ADS1115, sensors | C39: Shared 3A fuse | D39: Under 0.3A | E39: Common ground with the MOSFET board.

Sheet Setup Steps
A1: Build procedure
A2: Work top to bottom. Tick Done when finished.
A4: Step | B4: Phase | C4: Where | D4: What to do | E4: How (detail) | F4: Config / values | G4: Safety / notes | H4: Done
A5: 1 | B5: 0. Prepare | C5: Desk | D5: Fix the cart | E5: Resolve every item on the Cart Cross-check sheet before paying. | F5: Replace the 10 ohm resistors, heat shrink, fuses and leak sensor. Add the missing items. | G5: n/a | H5: No
A6: 2 | B6: 0. Prepare | C6: Motor / starter | D6: Record motor details | E6: Read the nameplate: HP, rated current (A), voltage. Photograph the existing starter wiring. | F6: Use the current to choose the overload range and to confirm the MCB and contactor ratings. | G6: Mains is OFF at the MCB while you look. | H6: No
A7: 3 | B7: 1. Bench (low voltage) | C7: Desk | D7: Flash the OS | E7: Flash Armbian or Debian minimal to the SanDisk card and boot the ROCK Pi S. | F7: balenaEtcher. First boot: set hostname, user, timezone. sudo apt update && sudo apt full-upgrade. | G7: No mains devices connected. | H7: No
A8: 4 | B8: 1. Bench (low voltage) | C8: Desk | D8: Install packages | E8: Install the tools the daemon needs. | F8: sudo apt install gpiod i2c-tools espeak-ng alsa-utils python3-venv sqlite3 chrony | G8: n/a | H8: No
A9: 5 | B9: 1. Bench (low voltage) | C9: Desk | D9: Enable I2C | E9: Enable the I2C overlay for the header pins. | F9: Use armbian-config > Hardware, enable the I2C overlay, reboot. Check with i2cdetect -l. | G9: Note the bus number. | H9: No
A10: 6 | B10: 1. Bench (low voltage) | C10: Desk | D10: Set up the RTC | E10: Wire the DS3231 and bind it. | F10: i2cdetect -y <bus> shows 68. echo ds3231 0x68 | sudo tee /sys/class/i2c-adapter/i2c-<n>/new_device, then hwclock -r and hwclock --systohc after NTP sync. | G10: LIR2032 or remove the charging resistor. | H10: No
A11: 7 | B11: 1. Bench (low voltage) | C11: Desk | D11: Test audio | E11: Plug in the hub, CM108 and speaker. | F11: aplay -l, then speaker-test -t wav -c 1, then espeak-ng -s 145 'Tank full' --stdout | aplay -q | G11: Set the default card in /etc/asound.conf. | H11: No
A12: 8 | B12: 1. Bench (low voltage) | C12: Desk | D12: Verify the GPIO map | E12: List the GPIO lines and match them to the header. | F12: gpioinfo, then compare with the Radxa pinout. Update the Wiring & Pinout sheet with the real chip and line numbers. | G12: Do this before wiring the relay. | H12: No
A13: 9 | B13: 1. Bench (low voltage) | C13: Desk | D13: Join Headscale | E13: Install the client and join your tailnet. | F13: curl -fsSL https://tailscale.com/install.sh | sh, then sudo tailscale up --login-server https://<your-headscale-url> --authkey <preauth-key> | G13: Set ACLs so only your devices reach port 8080. Enable key expiry. | H13: No
A14: 10 | B14: 1. Bench (low voltage) | C14: Desk | D14: Enable the watchdog | E14: Turn on the hardware watchdog with a 15 second timeout. | F14: In /etc/systemd/system.conf set RuntimeWatchdogSec=15s. In the service file set WatchdogSec=15 and Restart=always. | G14: Confirm /dev/watchdog exists. | H14: No
A15: 11 | B15: 2. ESP32 firmware | C15: Desk | D15: Flash the gateway | E15: Flash the ESP-NOW gateway sketch to ESP32 number 1. | F15: Arduino IDE or PlatformIO, board ESP32C3 Dev Module, USB CDC On Boot enabled. Gateway prints JSON lines to USB serial at 115200. | G15: Fix channel 1. Note its MAC. | H15: No
A16: 12 | B16: 2. ESP32 firmware | C16: Desk | D16: Flash the garden node | E16: Flash the node sketch to ESP32 number 2. | F16: Add the gateway MAC. Heartbeat every 5s. Set pump gates LOW in setup() before anything else. | G16: Pumps OFF if no ack for 60s. Max pump run 60s. | H16: No
... A34: 30 | B34: 9. Maintenance | C34: All | D34: Routine checks | E34: Monthly: press the RCCB test button, wipe the sensors, rinse the strainers, test the floats. | F34: Quarterly: check the UPS runtime, the fuses, and gland seals. | G34: Back up the SQLite file and config. | H34: No

Sheet Config Reference
A1: Configuration reference
A2: Suggested defaults. Edit the blue values to match your calibration. All need testing on your hardware.
A4: Area | B4: Parameter | C4: Value | D4: Where set | E4: Notes | F4: Status
A5: Power | B5: Head-end buck output | C5: 5.10 V | D5: Trimmer on the LM2596 | E5: Set with a multimeter before connecting the Pi. | F5: Fixed
A6: Power | B6: Garden buck output | C6: 5.0 V | D6: Trimmer on the MP1584 | E6: Feeds the ESP32 5V pin. | F6: Fixed
A7: Power | B7: Fuse sizes | C7: UPS 2A, head-end 5V 2A, garden 12V 3A | D7: Inline holders | E7: Fast-blow 5x20mm. | F7: Fixed
A8: I2C | B8: RTC address | C8: 0x68 | D8: DS3231 | E8: Shared bus with the OLED (0x3C). | F8: Fixed
A9: I2C | B9: ADC address | C9: 0x48 (0x49 for the second) | D9: ADDR pin | E9: ADDR to GND gives 0x48, to VDD gives 0x49. | F9: Fixed
A10: ADC | B10: ADS1115 gain | C10: 1 (+/-4.096 V) | D10: Firmware | E10: Covers the sensor's 3V max. | F10: Suggested
A11: ADC | B11: ADS1115 data rate | C11: 128 SPS | D11: Firmware | E11: Average 10 samples per reading. | F11: Suggested
A12: Soil | B12: Per-plant dry voltage (dry_V) | C12: To calibrate | D12: Config file | E12: Read in open air. | F12: Calibrate
A13: Soil | B13: Per-plant wet voltage (wet_V) | C13: To calibrate | D13: Config file | E13: Read in water. | F13: Calibrate
A14: Soil | B14: Sanity band | C14: [wet_V - 0.2, dry_V + 0.2] | D14: Daemon | E14: Outside the band means a broken or disconnected probe, so skip watering and announce. | F14: Calibrate
A15: Watering | B15: Default pump pulse | C15: 15 s | D15: API / daemon | E15: Manual pulse default. | F15: Suggested
... A35: Alerts | B35: Mobile alerts | C35: Telegram bot | D35: Daemon env file | E35: Overflow, dry-run, link lost, leak. | F35: Suggested

Sheet Commissioning Tests
A1: Commissioning tests
A2: Run in order. Use the real motor only after tests 1-9 pass. Electrician present for the first live run.
A4: Test | B4: Procedure | C4: Pass criteria | D4: Result | E4: Date / notes
A5: 1. Relay at boot | B5: Disconnect the motor. Power cycle the Pi 5 times and watch the relay. | C5: Relay never clicks on at boot or reset. | D5: Not run
A6: 2. Relay polarity | B6: Drive the relay from software and measure continuity. | C6: ON in software means closed. Matches the config. | D6: Not run
A7: 3. Interlock chain | B7: Open the Full float, then the Sump float, one at a time, while commanding ON. | C7: Relay drops out each time. The software reports which float tripped. | D7: Not run
A8: 4. Cut wire | B8: Disconnect the Full float wire. | C8: Chain opens. Motor cannot start. | D8: Not run
A9: 5. Pi crash | B9: Kill the daemon and hang the OS (echo c > /proc/sysrq-trigger). | C9: Watchdog resets within about 15 s. Relay stays OFF during the reset. | D9: Not run
A10: 6. Power cut | B10: Pull mains with the controller running. | C10: Pi stays up on the UPS. Pumps are off. No relay glitch on return. | D10: Not run
A11: 7. Max run watchdog | B11: Simulate a stuck Low float and run the motor with no load. | C11: Motor stops at 15 min and the lockout engages. | D11: Not run
A12: 8. Sanity band | B12: Unplug a soil sensor. | C12: Probe flagged as broken, watering skipped, alert spoken. | D12: Not run
A13: 9. Link loss | B13: Switch off the garden node. | C13: Gateway alerts after 30 s. Node pumps OFF after 60 s. | D13: Not run
A14: 10. Live motor, short run | B14: With the electrician present, run the motor for 1 minute. | C14: Current under the overload setting. No vibration or noise. | D14: Not run
A15: 11. Tank fill cycle | B15: Let the tank fill from low to full. | C15: Motor stops at the Full float. Software stops at the same time. | D15: Not run
A16: 12. Dry sump | B16: Lower the sump float by hand. | C16: Motor stops at once and an alert sounds. | D16: Not run
... A21: 17. Leak sensor | B21: Wet the probe. | C21: All pumps stop and an alert sounds. | D21: Not run

Sheet Cart Cross-check
A1: Amazon cart cross-check
A2: Based on the cart listing titles you shared. Items marked 'verify' need a look at the full product page.
A4: Cart item | B4: Issue | C4: Action | D4: Severity
A5: DEPOKE 10 Ohm resistors (50) | B5: Wrong value. The plan needs 10 kOhm pull-downs. | C5: Replace with 10 kOhm 1/4W. | D5: High
A6: ORGNER heat shrink 6-12 mm | B6: Too large for pump leads and small joints. | C6: Buy an assorted 2-6mm adhesive-lined kit. | D6: Medium
A7: ABSTXUOR USB 3.0 hub | B7: Slim hubs are usually bus-powered, with no DC input. | C7: Check for a DC jack. Replace if none. | D7: Medium
A8: 10A fuse combo | B8: 10A does not protect 2A and 3A rails. | C8: Buy 1A, 2A, 3A, 5A assorted 5x20mm fuses. | D8: High
A9: REL_35 water level sensor x3 | B9: Analog, exposed traces, corrodes, cannot connect to the Pi. | C9: Buy one digital leak sensor (LM393). | D9: Medium
A10: Pressure washer inlet filter x3 | B10: Hose-thread fittings do not fit mini pumps. | C10: Use an aquarium sponge or nylon mesh sleeve. | D10: Low
A11: Tycab cable ties x8 | B11: 800 ties; the plan needs 100. | C11: Set quantity to 1. | D11: Low
A12: TED TABBIES aquarium tube 70 m | B12: 4x6mm thin wall, kinks; the plan needs 4/7mm. | C12: Remove. The Grassland kit has 10 m. | D12: Low
A13: XYNO 30A contactor | B13: Unbranded and it switches the motor. | C13: Prefer L&T, Schneider or Siemens. | D13: High
A14: RCCB, amiciSmart SPD, KAYCEE MCB | B14: Protect people and the motor. SPD type not stated. | C14: Prefer Havells, Schneider, Legrand, L&T, Siemens. Confirm Type 2. Keep the GST invoice. | D14: High
A15: S J MJ1+ overload relay 6-10A | B15: Range suits about 1 HP or more. | C15: Read the motor nameplate. Match the contactor. | D15: High
... A28: Missing items | B28: microSD, CM108, speaker, 4th float, shielded cables, check valves, reducers, snubber, 10k resistors, two enclosures, DIN rail, terminal blocks, 2.5mm2 wire, PG9/PG11 glands, perfboard. | C28: Add these before ordering. | D28: High
